[
    {
        "user_id": "513077399228702720",
        "settings": null,
        "metadata": {
            "team_name": "Rain City Bitch Pigeons™",
            "show_mascots": "off",
            "mention_pn": "on",
            "mascot_message_emotion_leg_1": "victory",
            "mascot_item_type_id_leg_9": "chum",
            "mascot_item_type_id_leg_8": "chum",
            "mascot_item_type_id_leg_7": "chum",
            "mascot_item_type_id_leg_6": "chum",
            "mascot_item_type_id_leg_5": "chum",
            "mascot_item_type_id_leg_4": "chum",
            "mascot_item_type_id_leg_3": "chum",
            "mascot_item_type_id_leg_2": "chum",
            "mascot_item_type_id_leg_17": "chum",
            "mascot_item_type_id_leg_16": "chum",
            "mascot_item_type_id_leg_15": "chum",
            "mascot_item_type_id_leg_14": "chum",
            "mascot_item_type_id_leg_13": "chum",
            "mascot_item_type_id_leg_12": "chum",
            "mascot_item_type_id_leg_11": "chum",
            "mascot_item_type_id_leg_10": "chum",
            "mascot_item_type_id_leg_1": "chum",
            "avatar": "https://sleepercdn.com/uploads/8e9910db69f06c41b69bb17c2671bdbc",
            "allow_pn": "on"
        },
        "league_id": "649647301366755328",
        "is_owner": true,
        "is_bot": false,
        "display_name": "cgustafson",
        "avatar": "dab9a38bfb2aff3e54ab1abc3dfc3e56"
    },
    {
        "user_id": "605917755098619904",
        "settings": null,
        "metadata": {
            "team_name": "Kamaravirus",
            "mention_pn": "on",
            "mascot_message_emotion_leg_1": "dancing",
            "mascot_item_type_id_leg_9": "titan-up",
            "mascot_item_type_id_leg_8": "titan-up",
            "mascot_item_type_id_leg_7": "titan-up",
            "mascot_item_type_id_leg_6": "titan-up",
            "mascot_item_type_id_leg_5": "titan-up",
            "mascot_item_type_id_leg_4": "titan-up",
            "mascot_item_type_id_leg_3": "titan-up",
            "mascot_item_type_id_leg_2": "titan-up",
            "mascot_item_type_id_leg_18": "titan-up",
            "mascot_item_type_id_leg_17": "titan-up",
            "mascot_item_type_id_leg_16": "titan-up",
            "mascot_item_type_id_leg_15": "titan-up",
            "mascot_item_type_id_leg_14": "titan-up",
            "mascot_item_type_id_leg_13": "titan-up",
            "mascot_item_type_id_leg_12": "titan-up",
            "mascot_item_type_id_leg_11": "titan-up",
            "mascot_item_type_id_leg_10": "titan-up",
            "mascot_item_type_id_leg_1": "titan-up",
            "avatar": "https://sleepercdn.com/uploads/f6cf7ea3178d72f9ce3868b9c1c3ae09.jpg",
            "allow_pn": "on"
        },
        "league_id": "649647301366755328",
        "is_owner": null,
        "is_bot": false,
        "display_name": "nickdesimone01",
        "avatar": "b521c3934da4e28f6bf7eefea318b4e8"
    },
    {
        "user_id": "649650143385186304",
        "settings": null,
        "metadata": {
            "team_name": "flavortown fuccbois",
            "mention_pn": "on",
            "avatar": "https://sleepercdn.com/uploads/f1b8f6007c5c5782e1fdb250cf95abf7.jpg",
            "allow_pn": "on"
        },
        "league_id": "649647301366755328",
        "is_owner": null,
        "is_bot": false,
        "display_name": "kevingay",
        "avatar": "d5f25fade42c54e135cf11f72446f530"
    },
    {
        "user_id": "649654898559905792",
        "settings": null,
        "metadata": {
            "team_name": "Epstein Islanders",
            "mention_pn": "on",
            "avatar": "https://sleepercdn.com/uploads/c5bd61ec2a02d4d5422842c83112ddc7.jpg",
            "allow_pn": "on"
        },
        "league_id": "649647301366755328",
        "is_owner": null,
        "is_bot": false,
        "display_name": "KCharyszyn",
        "avatar": "cde6983dd133c3387e907531cdeed129"
    },
    {
        "user_id": "649661825167765504",
        "settings": null,
        "metadata": {
            "team_name": "Clyde and Go Seek",
            "mention_pn": "on",
            "mascot_message_emotion_leg_1": "dancing",
            "mascot_item_type_id_leg_9": "titan-up",
            "mascot_item_type_id_leg_8": "titan-up",
            "mascot_item_type_id_leg_7": "titan-up",
            "mascot_item_type_id_leg_6": "titan-up",
            "mascot_item_type_id_leg_5": "titan-up",
            "mascot_item_type_id_leg_4": "titan-up",
            "mascot_item_type_id_leg_3": "titan-up",
            "mascot_item_type_id_leg_2": "titan-up",
            "mascot_item_type_id_leg_17": "titan-up",
            "mascot_item_type_id_leg_16": "titan-up",
            "mascot_item_type_id_leg_15": "titan-up",
            "mascot_item_type_id_leg_14": "titan-up",
            "mascot_item_type_id_leg_13": "titan-up",
            "mascot_item_type_id_leg_12": "titan-up",
            "mascot_item_type_id_leg_11": "titan-up",
            "mascot_item_type_id_leg_10": "titan-up",
            "mascot_item_type_id_leg_1": "titan-up",
            "avatar": "https://sleepercdn.com/uploads/d896a54b3d5dcb43ed78b6e0b8b263a2.jpg",
            "allow_pn": "on"
        },
        "league_id": "649647301366755328",
        "is_owner": null,
        "is_bot": false,
        "display_name": "Cgusty30",
        "avatar": "8bdcc29cc1e5c38de4a30d91e4bfdebe"
    },
    {
        "user_id": "649687722881019904",
        "settings": null,
        "metadata": {
            "team_name": "Uber Yak",
            "mention_pn": "on",
            "mascot_message_emotion_leg_1": "idle",
            "mascot_item_type_id_leg_9": "chum",
            "mascot_item_type_id_leg_8": "chum",
            "mascot_item_type_id_leg_7": "chum",
            "mascot_item_type_id_leg_6": "chum",
            "mascot_item_type_id_leg_5": "chum",
            "mascot_item_type_id_leg_4": "chum",
            "mascot_item_type_id_leg_3": "chum",
            "mascot_item_type_id_leg_2": "chum",
            "mascot_item_type_id_leg_18": "chum",
            "mascot_item_type_id_leg_17": "chum",
            "mascot_item_type_id_leg_16": "chum",
            "mascot_item_type_id_leg_15": "chum",
            "mascot_item_type_id_leg_14": "chum",
            "mascot_item_type_id_leg_13": "chum",
            "mascot_item_type_id_leg_12": "chum",
            "mascot_item_type_id_leg_11": "chum",
            "mascot_item_type_id_leg_10": "chum",
            "mascot_item_type_id_leg_1": "chum",
            "avatar": "https://sleepercdn.com/uploads/61090b4e4d3aa5e105457ad2a280ac2e",
            "allow_pn": "on"
        },
        "league_id": "649647301366755328",
        "is_owner": null,
        "is_bot": false,
        "display_name": "cjastrzembski",
        "avatar": "b6f7eee9c000b1d41716eb7fa8608042"
    },
    {
        "user_id": "649709251400400896",
        "settings": null,
        "metadata": {
            "team_name": "Shanes ur dad",
            "mention_pn": "on",
            "avatar": "https://sleepercdn.com/uploads/bf7b9caa35f5ef13c6de78bdc9e235a3.jpg",
            "allow_pn": "on"
        },
        "league_id": "649647301366755328",
        "is_owner": null,
        "is_bot": false,
        "display_name": "DowntownKuz",
        "avatar": "2c96a24c53caa6c734a119e589ad20e6"
    },
    {
        "user_id": "649745894043934720",
        "settings": null,
        "metadata": {
            "team_name": "Xandrews rugg and tugg ",
            "mention_pn": "on",
            "mascot_message_emotion_leg_1": "victory",
            "mascot_item_type_id_leg_9": "pizza",
            "mascot_item_type_id_leg_8": "pizza",
            "mascot_item_type_id_leg_7": "pizza",
            "mascot_item_type_id_leg_6": "pizza",
            "mascot_item_type_id_leg_5": "pizza",
            "mascot_item_type_id_leg_4": "pizza",
            "mascot_item_type_id_leg_3": "pizza",
            "mascot_item_type_id_leg_2": "pizza",
            "mascot_item_type_id_leg_17": "pizza",
            "mascot_item_type_id_leg_16": "pizza",
            "mascot_item_type_id_leg_15": "pizza",
            "mascot_item_type_id_leg_14": "pizza",
            "mascot_item_type_id_leg_13": "pizza",
            "mascot_item_type_id_leg_12": "pizza",
            "mascot_item_type_id_leg_11": "pizza",
            "mascot_item_type_id_leg_10": "pizza",
            "mascot_item_type_id_leg_1": "pizza",
            "allow_pn": "on"
        },
        "league_id": "649647301366755328",
        "is_owner": null,
        "is_bot": false,
        "display_name": "nickmottola",
        "avatar": "d74cfa986aca87ce83d07d975b83fb7d"
    },
    {
        "user_id": "649760561730498560",
        "settings": null,
        "metadata": {
            "user_message_pn": "on",
            "transaction_waiver": "on",
            "transaction_trade": "on",
            "transaction_free_agent": "on",
            "transaction_commissioner": "on",
            "trade_block_pn": "on",
            "team_name_update": "on",
            "team_name": "Washington Foreskins",
            "player_nickname_update": "off",
            "player_like_pn": "on",
            "mention_pn": "on",
            "mascot_message": "on",
            "join_voice_pn": "on",
            "avatar": "https://sleepercdn.com/uploads/d734cd226bad5cbabb195a0ddcf98be2.jpg",
            "allow_pn": "on"
        },
        "league_id": "649647301366755328",
        "is_owner": null,
        "is_bot": false,
        "display_name": "MaxLurie",
        "avatar": "d74cfa986aca87ce83d07d975b83fb7d"
    },
    {
        "user_id": "649802014125019136",
        "settings": null,
        "metadata": {
            "mention_pn": "on",
            "mascot_message_emotion_leg_1": "idle",
            "mascot_item_type_id_leg_9": "goat",
            "mascot_item_type_id_leg_8": "goat",
            "mascot_item_type_id_leg_7": "goat",
            "mascot_item_type_id_leg_6": "goat",
            "mascot_item_type_id_leg_5": "goat",
            "mascot_item_type_id_leg_4": "goat",
            "mascot_item_type_id_leg_3": "goat",
            "mascot_item_type_id_leg_2": "goat",
            "mascot_item_type_id_leg_18": "goat",
            "mascot_item_type_id_leg_17": "goat",
            "mascot_item_type_id_leg_16": "goat",
            "mascot_item_type_id_leg_15": "goat",
            "mascot_item_type_id_leg_14": "goat",
            "mascot_item_type_id_leg_13": "goat",
            "mascot_item_type_id_leg_12": "goat",
            "mascot_item_type_id_leg_11": "goat",
            "mascot_item_type_id_leg_10": "goat",
            "mascot_item_type_id_leg_1": "goat",
            "allow_pn": "on"
        },
        "league_id": "649647301366755328",
        "is_owner": null,
        "is_bot": false,
        "display_name": "peterclear97",
        "avatar": "f998112053e26d52e49b968216d74b19"
    },
    {
        "user_id": "649803719025733632",
        "settings": null,
        "metadata": {
            "team_name": "Kaeperflick My Bean",
            "mention_pn": "on",
            "allow_pn": "on"
        },
        "league_id": "649647301366755328",
        "is_owner": null,
        "is_bot": false,
        "display_name": "Kaeperflickmybean",
        "avatar": "9f2f265e886d5a55d670236275e88fe0"
    },
    {
        "user_id": "649818689171968000",
        "settings": null,
        "metadata": {
            "team_name": "Some Prosciutto",
            "mention_pn": "on",
            "mascot_message_emotion_leg_1": "idle",
            "mascot_item_type_id_leg_9": "taco",
            "mascot_item_type_id_leg_8": "taco",
            "mascot_item_type_id_leg_7": "taco",
            "mascot_item_type_id_leg_6": "taco",
            "mascot_item_type_id_leg_5": "taco",
            "mascot_item_type_id_leg_4": "taco",
            "mascot_item_type_id_leg_3": "taco",
            "mascot_item_type_id_leg_2": "taco",
            "mascot_item_type_id_leg_18": "taco",
            "mascot_item_type_id_leg_17": "taco",
            "mascot_item_type_id_leg_16": "taco",
            "mascot_item_type_id_leg_15": "taco",
            "mascot_item_type_id_leg_14": "taco",
            "mascot_item_type_id_leg_13": "taco",
            "mascot_item_type_id_leg_12": "taco",
            "mascot_item_type_id_leg_11": "taco",
            "mascot_item_type_id_leg_10": "taco",
            "mascot_item_type_id_leg_1": "taco",
            "avatar": "https://sleepercdn.com/uploads/60bd6276d283bfaf1ea37ebfa8729d0c.jpg",
            "allow_pn": "on"
        },
        "league_id": "649647301366755328",
        "is_owner": null,
        "is_bot": false,
        "display_name": "jsawyer97",
        "avatar": "00c60af588f23afbc094f0d7ebe70650"
    }
]
